ghstar/__init__.py
ghstar/ghstar.py
ghstar-0.2.0.dist-info/entry_points.txt
ghstar-0.2.0.dist-info/LICENSE.md
ghstar-0.2.0.dist-info/WHEEL
ghstar-0.2.0.dist-info/METADATA
ghstar-0.2.0.dist-info/RECORD
