Metadata-Version: 2.1
Name: ghstar
Version: 0.2.0
Summary: Star GitHub repos from the command line
Home-page: https://www.github.com/gokulsoumya/ghstar
License: MIT
Keywords: github,stars
Author: Gokul
Author-email: gokulps15@gmail.com
Requires-Python: >=3.5,<4.0
Classifier: Environment :: Console
Classifier: Intended Audience :: Developers
Classifier: License :: OSI Approved :: MIT License
Classifier: Programming Language :: Python :: 3
Classifier: Programming Language :: Python :: 3.5
Classifier: Programming Language :: Python :: 3.6
Classifier: Programming Language :: Python :: 3.7
Classifier: Topic :: Terminals
Classifier: Topic :: Utilities
Requires-Dist: requests (>=2.22,<3.0)
Project-URL: Repository, https://www.github.com/gokulsoumya/ghstar
